{
  "date": "2025-09-19",
  "timestamp": "2025-09-19T21:20:42.956000+00:00",
  "index": 18,
  "text": "roky? \n  \n  ja mam vplane to mat osvojene do tyzdna, kedze na tom pracuejm od 18 rokov, aby osm objavil seba v plnej krase, a tu ju vidime. \n  \n  neviem na co by som mal cakat roky, ked viem akos a dominancia sprava.. a konecne som pochopil ako sa da exekuovat. odhodlanim.",
  "word_count": 50,
  "source_path": "data/chronology/2025-09-19.md",
  "diacritic_ratio": 0.0,
  "has_placeholder": false,
  "has_link": false,
  "has_code": false,
  "ai_style": false,
  "author_guess": "adam",
  "needs_review": false
}