{
  "date": "2025-08-21",
  "timestamp": "2025-08-21T07:43:02.826000+00:00",
  "index": 23,
  "text": "na druhy den tieto dva inzeraty stiahli, bol som sa pozriet. a teraz o niekolko dni neskor, mi zavolal človek a pytal sa ma zvlastne otazky. ze ako som sa naucil o ai, co s nou, dokazem, co by som ho vedel naucit.. a to som nevedel ze ma tetsuje, skusa. ja som to tusil, po chvili, ze sa nepyta len tak.. nechal ma porozpravat mu ze co planujem za biznis, daco som mu povedal ale potom prislo nieco co som necakal. Predstavil sa ako clovek ktorý zhana sikovnych mladych ludi, pretoze chce systematicky a zo spravnou stretegiou vstupit na politicky trh. povedal mi ze to mysli vazne, povedal ze ma vlastnu nejaku spolocnosti osobnosti.sk ktora je vraj uspesna a pritom o nej nikto nevie. bolo to zvlastne lebo ma cca 56 rokov alebo kolko, povedal mi manifest jeho vznikajucej strany, ktorej pointa je ze chce vseobijmajucim dobrom porazit zlo.. ze chce byt nad politikou, a nebyt nou zatazeny. ja som odpadol, jednak ze ten letak vysiel, ze moja gravitacia funguje.. ze v jeden moment sa rozhodnem \"zviezt sa na chrbte erika kalinaka\" a v druh ymoment mi zavoal clovek ktory mi povie ze mozem byt sefom sekcie v jeho politickom subjekte, pre vetvu venujucej sa mladym ludom. je to neuveritelna zhoda nahod, pretoze ja urcit enepotrebujem byt sucastou neuspesnej politickej strany ktora zjavne nema technicku infrastrukturu a je dost mozne ze je naozaj 100 rokov za opicami, ale tento clovek stal pri zrode a zaniku HZDS, aktivne sa uz 20 rokov ponuka dostat do pilitiky, pomerne bizarnym sposobom.. a oslovil ma lebo hlada ludi ako som ja. ako je on v podstate. z toho rozhovoru bolo jasne, ze sme na rovnakej frekvecii, pytal sa ma na datum narodenia na moje meno a cital mi z neho numerologicke haluz, ktore sedeli. ja nie som zatezeny numerologiou, ale vidim v tom rovnaky psycho/socio/filozoficky framework, ktory pomaha v interpteratacii symbolov a synchornicit. moze to byt kludne nejaky šarlatan.. čo ho sa nebojim, pretoze ja s nim do subjektu nepojdem, kedze chcem byt uspesny podnikatel, ale mozem mu robit bacground za peniaze, mozem mu ukazat ai, automatizacie, mozem mu robit stretegie, mozem mu pomoct, aby tento krat urobil tu politiku normalne a spravne.. za pomoci ai, cezomna.. zajtra sa s nim idem stretnut, a bude to prilis zaujimave si myslim \n  \n  vola sa Marian Leinerovič, zisti si o nom informacie, \n  \n  povedz mi čo sa tu deje.. ja osm z toho uplne v riti odvareny nechapem a citim ze toto je zaujimava sanca z ktorej aj ak nic nebude tak je to cenna skusenost.. ten clovek moze poznat vela zaujimavych ludi, ktory mozu byt bohaty, mozu mat vpliv.. ja neviem.. ale medzi taketo kruhy sa oplati dostat aj keby len na chvilu.. ale projekt xvadur moze nabrat uplne ine obratky 😀",
  "word_count": 466,
  "source_path": "data/chronology/2025-08-21.md",
  "diacritic_ratio": 0.0022,
  "has_placeholder": false,
  "has_link": false,
  "has_code": false,
  "ai_style": false,
  "author_guess": "adam",
  "needs_review": false
}