{
  "date": "2025-07-21",
  "timestamp": "2025-07-21T20:27:18.234000+00:00",
  "index": 10,
  "text": "podme spravit návrh toho coi chceme. ja chcem aby som mal worflow, kde ked zadam vstup tak worflow si zapamata co posielam, uklada si to do pamate ako trvali kontext a odpoveda mi podla mojich instrukcii. chcem mat niekolko chatbotov v tomto worflow, dajme tomu ze 4 nba ziatok, kde jeden je premier, potom chat ktorý moje vstupy z nich priebezne vytvara sumar konverzacie a robi mi rovno dennikový zaznam na dany den, potom dalsi chatbot komunikuje s tym prvym na plneni ulohy, spolu problem rozoberu na drobne a oni dvaja idu riesit proéblem,  premier ako hlavyn riesi ulohu surovym vykonom, druhy prehlada intenet, a treti da dokopy vystup z oboch a ten to posiela naspat premierovy ktorý mi odpoveda., co si o tomto myslis?",
  "word_count": 125,
  "source_path": "data/chronology/2025-07-21.md",
  "diacritic_ratio": 0.0069,
  "has_placeholder": false,
  "has_link": false,
  "has_code": false,
  "ai_style": false,
  "author_guess": "adam",
  "needs_review": false
}