{
  "date": "2025-09-04",
  "timestamp": "2025-09-04T07:55:13.978000+00:00",
  "index": 1,
  "text": "dobre.. teraz ked sa vratime do sucastnosti, tak povedz, cim som si presiel a co som za cloveka ked mas tieto informacie o mne, co by si mi kriticky na to povedal kebyze mas byt v roli foundera, a rozpravas sa somnou ako z nadejnym podnikatelom?",
  "word_count": 46,
  "source_path": "data/chronology/2025-09-04.md",
  "diacritic_ratio": 0.0,
  "has_placeholder": false,
  "has_link": false,
  "has_code": false,
  "ai_style": false,
  "author_guess": "adam",
  "needs_review": false
}