{
  "description": "Denné kvantitatívne metriky pre XP výpočet v xvadur režime",
  "format": {
    "date": "YYYY-MM-DD",
    "word_count": 0,
    "prompt_count": 0,
    "complexity_avg": 0,
    "temporal_references": 0,
    "recursive_depth_max": 0,
    "sentiment_distribution": {
      "positive": 0,
      "negative": 0,
      "neutral": 0
    },
    "rag_queries": 0,
    "xp_earned": 0
  },
  "data": [
    {
      "date": "2025-12-01",
      "sessions": 3,
      "word_count": 18207,
      "prompt_count": 40,
      "complexity_avg": 9.67,
      "temporal_references": 58,
      "recursive_depth_max": 3.0,
      "sentiment_distribution": {
        "positive": 3,
        "negative": 0,
        "neutral": 0
      },
      "rag_queries": 0,
      "xp_earned": 19.54,
      "session_ids": [
        "2025-12-01_09:45",
        "2025-12-01_10:30",
        "2025-12-01_11:00"
      ]
    }
  ]
}